<?xml version='1.0' encoding='UTF-8'?>
<object id="4wfMmFEBU48K" classes="specific-data" acceptedChildren=":Proteus-none" acceptedParents="information-requirement">
  <properties>
    <stringProperty name=":Proteus-name" category="general"><![CDATA[cantidad]]></stringProperty>
    <markdownProperty name="description" category="general"><![CDATA[a]]></markdownProperty>
    <markdownProperty name="comments" category="comments"><![CDATA[]]></markdownProperty>
  </properties>
  <children/>
</object>
