<?xml version='1.0' encoding='UTF-8'?>
<object id="68nTar8kYp7H" classes="specific-data" acceptedChildren=":Proteus-none" acceptedParents="information-requirement">
  <properties>
    <stringProperty name=":Proteus-name" category="general"><![CDATA[númeroDeReferencia]]></stringProperty>
    <markdownProperty name="description" category="general"><![CDATA[Identificador único del método.]]></markdownProperty>
    <markdownProperty name="comments" category="comments"><![CDATA[]]></markdownProperty>
  </properties>
  <children/>
</object>
